django_oso/__init__.py
django_oso/apps.py
django_oso/auth.py
django_oso/decorators.py
django_oso/middleware.py
django_oso/models.py
django_oso/oso.py
django_oso/partial.py
django_oso/settings.py
django_oso-0.27.0.dist-info/METADATA
django_oso-0.27.0.dist-info/WHEEL
django_oso-0.27.0.dist-info/entry_points.txt
django_oso-0.27.0.dist-info/top_level.txt
django_oso-0.27.0.dist-info/RECORD
