Metadata-Version: 2.1
Name: django-oso
Version: 0.27.0
Summary: oso django integration
Home-page: https://www.osohq.com/
Author: Oso Security, Inc.
License: UNKNOWN
Project-URL: Source, https://github.com/osohq/oso/tree/main/languages/python/django-oso
Platform: UNKNOWN
Classifier: Development Status :: 4 - Beta
Classifier: Programming Language :: Python :: 3.7
Classifier: License :: OSI Approved :: Apache Software License
Requires-Python: >=3.7
Requires-Dist: oso (~=0.27.0)
Requires-Dist: django (>=2.2)
